pmole/__init__.py
pmole/cli.py
pmole/parser.py
pmole-0.2.0.dist-info/LICENSE
pmole-0.2.0.dist-info/METADATA
pmole-0.2.0.dist-info/WHEEL
pmole-0.2.0.dist-info/entry_points.txt
pmole-0.2.0.dist-info/top_level.txt
pmole-0.2.0.dist-info/RECORD
