Metadata-Version: 2.2
Name: pmole
Version: 0.2.0
Summary: Project Mole
Author-email: Tsotne Otanadze <otanadzetsotne@gmail.com>
License: MIT
Classifier: Programming Language :: Python :: 3
Classifier: License :: OSI Approved :: MIT License
Classifier: Operating System :: OS Independent
Requires-Python: >=3.8
License-File: LICENSE
Provides-Extra: dev
Requires-Dist: pytest>=7.0.0; extra == "dev"
Requires-Dist: flake8>=6.0.0; extra == "dev"
